coreason_aegis/__init__.py
coreason_aegis/main.py
coreason_aegis/masking.py
coreason_aegis/models.py
coreason_aegis/reidentifier.py
coreason_aegis/scanner.py
coreason_aegis/server.py
coreason_aegis/utils/__init__.py
coreason_aegis/utils/logger.py
coreason_aegis/vault.py
coreason_aegis-0.4.0.dist-info/METADATA
coreason_aegis-0.4.0.dist-info/WHEEL
coreason_aegis-0.4.0.dist-info/licenses/LICENSE
coreason_aegis-0.4.0.dist-info/licenses/NOTICE
coreason_aegis-0.4.0.dist-info/RECORD
