Metadata-Version: 2.4
Name: coreason_aegis
Version: 0.4.0
Summary: bidirectional privacy filter that sits between the CoReason platform and the external world
License: # The Prosperity Public License 3.0.0
License-File: LICENSE
License-File: NOTICE
Author: Gowtham A Rao
Author-email: gowtham.rao@coreason.ai
Requires-Python: >=3.11
Classifier: License :: Other/Proprietary License
Classifier: Programming Language :: Python :: 3.12
Classifier: Operating System :: OS Independent
Requires-Dist: aiofiles (>=25.1.0,<26.0.0)
Requires-Dist: anyio (>=4.12.1,<5.0.0)
Requires-Dist: cachetools (>=6.2.6,<7.0.0)
Requires-Dist: coreason-identity (>=0.4.2,<0.5.0)
Requires-Dist: faker (>=40.1.2,<41.0.0)
Requires-Dist: fastapi (>=0.115.0,<0.116.0)
Requires-Dist: httpx (>=0.28.1,<0.29.0)
Requires-Dist: jaraco-context (>=6.1.0,<7.0.0)
Requires-Dist: loguru (>=0.7.2,<0.8.0)
Requires-Dist: presidio-analyzer (>=2.2.360,<3.0.0)
Requires-Dist: presidio-anonymizer (>=2.2.360,<3.0.0)
Requires-Dist: pydantic (>=2.12.5,<3.0.0)
Requires-Dist: pydantic-settings (>=2.12.0,<3.0.0)
Requires-Dist: types-aiofiles (>=25.1.0.20251011,<26.0.0.0)
Requires-Dist: uvicorn[standard] (>=0.27.0,<0.28.0)
Project-URL: Documentation, https://github.com/CoReason-AI/coreason_aegis
Project-URL: Homepage, https://github.com/CoReason-AI/coreason_aegis
Project-URL: Repository, https://github.com/CoReason-AI/coreason_aegis
